protogen_beeper_Prootzel/__init__.py
protogen_beeper_Prootzel/protogen.py
src/__init__.py
src/protogen.py
protogen_beeper-0.0.3.dist-info/METADATA
protogen_beeper-0.0.3.dist-info/WHEEL
protogen_beeper-0.0.3.dist-info/top_level.txt
protogen_beeper-0.0.3.dist-info/RECORD
