Metadata-Version: 2.1
Name: protogen_beeper
Version: 0.0.3
Summary: A library to test how to develop modules
Home-page: https://github.com/Prootzel/Protogen_Test_Library
Author: Prootzel
Author-email: lirkel123@gmail.com
Classifier: Programming Language :: Python :: 3
Classifier: License :: OSI Approved :: MIT License
Classifier: Operating System :: OS Independent
